MANIFEST.in
README.md
requirements.txt
setup.py
cascadis/__init__.py
cascadis/__main__.py
cascadis/api.py
cascadis/atx.py
cascadis/auth.py
cascadis/environ.py
cascadis/misc.py
cascadis/utils.py
cascadis/views.py
cascadis/viewutils.py
cascadis.egg-info/PKG-INFO
cascadis.egg-info/SOURCES.txt
cascadis.egg-info/dependency_links.txt
cascadis.egg-info/entry_points.txt
cascadis.egg-info/not-zip-safe
cascadis.egg-info/requires.txt
cascadis.egg-info/top_level.txt
cascadis/cli/__init__.py
cascadis/cli/get.py
cascadis/cli/put.py
cascadis/cli/shell.py
cascadis/solutions/__init__.py
cascadis/solutions/inference.py
cascadis/solutions/legacy.py
cascadis/solutions/sessions.py
cascadis/templates/login.html
cascadis/templates/upload.html