Metadata-Version: 2.1
Name: cascadis
Version: 0.2.0
Summary: A simple content-addressed storage service.
Home-page: https://github.com/frozflame/cascadis
Author: frozflame
Author-email: frozflame@outlook.com
License: GNU General Public License (GPL)
Classifier: Programming Language :: Python
Classifier: Programming Language :: Python :: 3
Classifier: Programming Language :: Python :: 3.11
Classifier: Programming Language :: Python :: 3.12
Classifier: Programming Language :: Python :: 3.13
Requires-Dist: Flask~=3.0.3
Requires-Dist: joker-cast~=0.5.2
Requires-Dist: joker-filesys~=0.3.0
Requires-Dist: joker-flasky~=0.6.0
Requires-Dist: joker~=0.3.3
Requires-Dist: pymongo~=4.6.2
Requires-Dist: python-magic~=0.4.27
Requires-Dist: redis~=5.0.2
Requires-Dist: requests~=2.31.0
Requires-Dist: setuptools>=68.2.0
Requires-Dist: volkanic~=0.5.3
Requires-Dist: Werkzeug~=3.0.3
